django_ltree/__init__.py
django_ltree/apps.py
django_ltree/checks.py
django_ltree/fields.py
django_ltree/functions.py
django_ltree/lookups.py
django_ltree/managers.py
django_ltree/models.py
django_ltree/paths.py
django_ltree/migrations/0001_create_extension.py
django_ltree/migrations/__init__.py
greendeploy_django_ltree-0.5.3.dist-info/LICENSE
greendeploy_django_ltree-0.5.3.dist-info/METADATA
greendeploy_django_ltree-0.5.3.dist-info/WHEEL
greendeploy_django_ltree-0.5.3.dist-info/top_level.txt
greendeploy_django_ltree-0.5.3.dist-info/RECORD
