Metadata-Version: 2.1
Name: greendeploy-django-ltree
Version: 0.5.3
Summary: Django app to support ltree postgres extension
Home-page: https://github.com/GreenDeploy-io/greendeploy-django-ltree
Author: KimSia Sim
Author-email: kimsia@oppoin.com
Maintainer: Kimsia Sim
License: MIT
Project-URL: Source, https://github.com/GreenDeploy-io/greendeploy-django-ltree
Project-URL: Tracker, https://github.com/GreenDeploy-io/greendeploy-django-ltree/issues
Keywords: django,ltree,postgres
Classifier: Development Status :: 4 - Beta
Classifier: Framework :: Django
Classifier: Framework :: Django :: 1.11
Classifier: Framework :: Django :: 2.1
Classifier: Framework :: Django :: 2.2
Classifier: Intended Audience :: Developers
Classifier: Operating System :: OS Independent
Classifier: Programming Language :: Python
Classifier: Programming Language :: Python :: 2.7
Classifier: Programming Language :: Python :: 3
Classifier: Programming Language :: Python :: 3.5
Classifier: Programming Language :: Python :: 3.6
Classifier: Programming Language :: Python :: 3.7
Classifier: Programming Language :: Python :: 3.8
Requires-Python: >=2.7
License-File: LICENSE
Requires-Dist: django >=1.11
Requires-Dist: six
Provides-Extra: develop
Requires-Dist: twine ; extra == 'develop'
Requires-Dist: tox ; extra == 'develop'
